steely/__init__.py
steely/cronos/__init__.py
steely/design/__init__.py
steely/fastapi/__init__.py
steely/fastapi/recorder/__init__.py
steely/fastapi/recorder/curl.py
steely/fastapi/recorder/postman.py
steely/logger/__init__.py
steely/pprint/__init__.py
steely/scan/__init__.py
steely-1.0.1.5.dist-info/METADATA
steely-1.0.1.5.dist-info/WHEEL
steely-1.0.1.5.dist-info/licenses/LICENSE
steely-1.0.1.5.dist-info/RECORD
