Metadata-Version: 2.4
Name: steely
Version: 1.0.1.5
Summary: A Python debugging and analysis toolkit with beautiful, colorful terminal output. Provides decorators for automatic logging, execution timing, and real-time variable tracking.
Project-URL: Homepage, https://github.com/tomneto/steely
Project-URL: Documentation, https://github.com/tomneto/steely#readme
Project-URL: Repository, https://github.com/tomneto/steely
Project-URL: Issues, https://github.com/tomneto/steely/issues
Author: Tom Neto
License: MIT
License-File: LICENSE
Keywords: colored-output,debug,debugging,decorator,developer-tools,execution-time,inspect,logging,monitor,profiling,terminal,trace,tracing,variable-tracking
Classifier: Development Status :: 4 - Beta
Classifier: Environment :: Console
Classifier: Intended Audience :: Developers
Classifier: License :: OSI Approved :: MIT License
Classifier: Operating System :: OS Independent
Classifier: Programming Language :: Python :: 3
Classifier: Programming Language :: Python :: 3.9
Classifier: Programming Language :: Python :: 3.10
Classifier: Programming Language :: Python :: 3.11
Classifier: Programming Language :: Python :: 3.12
Classifier: Programming Language :: Python :: 3.13
Classifier: Topic :: Software Development :: Debuggers
Classifier: Topic :: Software Development :: Libraries :: Python Modules
Classifier: Topic :: Software Development :: Testing
Classifier: Topic :: System :: Logging
Classifier: Typing :: Typed
Requires-Python: >=3.9
Requires-Dist: fastapi
Requires-Dist: twine>=6.2.0
